{
  "region": "Europe",
  "iso": "LV",
  "name": "Latvia",
  "hasPostalCodes": true,
  "states": [
    {
      "name": "Aglonas novads",
      "iso": "LV-001",
      "category": "municipality"
    },
    {
      "name": "Aizkraukles novads",
      "iso": "LV-002",
      "category": "municipality"
    },
    {
      "name": "Aizputes novads",
      "iso": "LV-003",
      "category": "municipality"
    },
    {
      "name": "Aknīstes novads",
      "iso": "LV-004",
      "category": "municipality"
    },
    {
      "name": "Alojas novads",
      "iso": "LV-005",
      "category": "municipality"
    },
    {
      "name": "Alsungas novads",
      "iso": "LV-006",
      "category": "municipality"
    },
    {
      "name": "Alūksnes novads",
      "iso": "LV-007",
      "category": "municipality"
    },
    {
      "name": "Amatas novads",
      "iso": "LV-008",
      "category": "municipality"
    },
    {
      "name": "Apes novads",
      "iso": "LV-009",
      "category": "municipality"
    },
    {
      "name": "Auces novads",
      "iso": "LV-010",
      "category": "municipality"
    },
    {
      "name": "Ādažu novads",
      "iso": "LV-011",
      "category": "municipality"
    },
    {
      "name": "Babītes novads",
      "iso": "LV-012",
      "category": "municipality"
    },
    {
      "name": "Baldones novads",
      "iso": "LV-013",
      "category": "municipality"
    },
    {
      "name": "Baltinavas novads",
      "iso": "LV-014",
      "category": "municipality"
    },
    {
      "name": "Balvu novads",
      "iso": "LV-015",
      "category": "municipality"
    },
    {
      "name": "Bauskas novads",
      "iso": "LV-016",
      "category": "municipality"
    },
    {
      "name": "Beverīnas novads",
      "iso": "LV-017",
      "category": "municipality"
    },
    {
      "name": "Brocēnu novads",
      "iso": "LV-018",
      "category": "municipality"
    },
    {
      "name": "Burtnieku novads",
      "iso": "LV-019",
      "category": "municipality"
    },
    {
      "name": "Carnikavas novads",
      "iso": "LV-020",
      "category": "municipality"
    },
    {
      "name": "Cesvaines novads",
      "iso": "LV-021",
      "category": "municipality"
    },
    {
      "name": "Cēsu novads",
      "iso": "LV-022",
      "category": "municipality"
    },
    {
      "name": "Ciblas novads",
      "iso": "LV-023",
      "category": "municipality"
    },
    {
      "name": "Dagdas novads",
      "iso": "LV-024",
      "category": "municipality"
    },
    {
      "name": "Daugavpils novads",
      "iso": "LV-025",
      "category": "municipality"
    },
    {
      "name": "Dobeles novads",
      "iso": "LV-026",
      "category": "municipality"
    },
    {
      "name": "Dundagas novads",
      "iso": "LV-027",
      "category": "municipality"
    },
    {
      "name": "Durbes novads",
      "iso": "LV-028",
      "category": "municipality"
    },
    {
      "name": "Engures novads",
      "iso": "LV-029",
      "category": "municipality"
    },
    {
      "name": "Ērgļu novads",
      "iso": "LV-030",
      "category": "municipality"
    },
    {
      "name": "Garkalnes novads",
      "iso": "LV-031",
      "category": "municipality"
    },
    {
      "name": "Grobiņas novads",
      "iso": "LV-032",
      "category": "municipality"
    },
    {
      "name": "Gulbenes novads",
      "iso": "LV-033",
      "category": "municipality"
    },
    {
      "name": "Iecavas novads",
      "iso": "LV-034",
      "category": "municipality"
    },
    {
      "name": "Ikšķiles novads",
      "iso": "LV-035",
      "category": "municipality"
    },
    {
      "name": "Ilūkstes novads",
      "iso": "LV-036",
      "category": "municipality"
    },
    {
      "name": "Inčukalna novads",
      "iso": "LV-037",
      "category": "municipality"
    },
    {
      "name": "Jaunjelgavas novads",
      "iso": "LV-038",
      "category": "municipality"
    },
    {
      "name": "Jaunpiebalgas novads",
      "iso": "LV-039",
      "category": "municipality"
    },
    {
      "name": "Jaunpils novads",
      "iso": "LV-040",
      "category": "municipality"
    },
    {
      "name": "Jelgavas novads",
      "iso": "LV-041",
      "category": "municipality"
    },
    {
      "name": "Jēkabpils novads",
      "iso": "LV-042",
      "category": "municipality"
    },
    {
      "name": "Kandavas novads",
      "iso": "LV-043",
      "category": "municipality"
    },
    {
      "name": "Kārsavas novads",
      "iso": "LV-044",
      "category": "municipality"
    },
    {
      "name": "Kocēnu novads",
      "iso": "LV-045",
      "category": "municipality"
    },
    {
      "name": "Kokneses novads",
      "iso": "LV-046",
      "category": "municipality"
    },
    {
      "name": "Krāslavas novads",
      "iso": "LV-047",
      "category": "municipality"
    },
    {
      "name": "Krimuldas novads",
      "iso": "LV-048",
      "category": "municipality"
    },
    {
      "name": "Krustpils novads",
      "iso": "LV-049",
      "category": "municipality"
    },
    {
      "name": "Kuldīgas novads",
      "iso": "LV-050",
      "category": "municipality"
    },
    {
      "name": "Ķeguma novads",
      "iso": "LV-051",
      "category": "municipality"
    },
    {
      "name": "Ķekavas novads",
      "iso": "LV-052",
      "category": "municipality"
    },
    {
      "name": "Lielvārdes novads",
      "iso": "LV-053",
      "category": "municipality"
    },
    {
      "name": "Limbažu novads",
      "iso": "LV-054",
      "category": "municipality"
    },
    {
      "name": "Līgatnes novads",
      "iso": "LV-055",
      "category": "municipality"
    },
    {
      "name": "Līvānu novads",
      "iso": "LV-056",
      "category": "municipality"
    },
    {
      "name": "Lubānas novads",
      "iso": "LV-057",
      "category": "municipality"
    },
    {
      "name": "Ludzas novads",
      "iso": "LV-058",
      "category": "municipality"
    },
    {
      "name": "Madonas novads",
      "iso": "LV-059",
      "category": "municipality"
    },
    {
      "name": "Mazsalacas novads",
      "iso": "LV-060",
      "category": "municipality"
    },
    {
      "name": "Mālpils novads",
      "iso": "LV-061",
      "category": "municipality"
    },
    {
      "name": "Mārupes novads",
      "iso": "LV-062",
      "category": "municipality"
    },
    {
      "name": "Mērsraga novads",
      "iso": "LV-063",
      "category": "municipality"
    },
    {
      "name": "Naukšēnu novads",
      "iso": "LV-064",
      "category": "municipality"
    },
    {
      "name": "Neretas novads",
      "iso": "LV-065",
      "category": "municipality"
    },
    {
      "name": "Nīcas novads",
      "iso": "LV-066",
      "category": "municipality"
    },
    {
      "name": "Ogres novads",
      "iso": "LV-067",
      "category": "municipality"
    },
    {
      "name": "Olaines novads",
      "iso": "LV-068",
      "category": "municipality"
    },
    {
      "name": "Ozolnieku novads",
      "iso": "LV-069",
      "category": "municipality"
    },
    {
      "name": "Pārgaujas novads",
      "iso": "LV-070",
      "category": "municipality"
    },
    {
      "name": "Pāvilostas novads",
      "iso": "LV-071",
      "category": "municipality"
    },
    {
      "name": "Pļaviņu novads",
      "iso": "LV-072",
      "category": "municipality"
    },
    {
      "name": "Preiļu novads",
      "iso": "LV-073",
      "category": "municipality"
    },
    {
      "name": "Priekules novads",
      "iso": "LV-074",
      "category": "municipality"
    },
    {
      "name": "Priekuļu novads",
      "iso": "LV-075",
      "category": "municipality"
    },
    {
      "name": "Raunas novads",
      "iso": "LV-076",
      "category": "municipality"
    },
    {
      "name": "Rēzeknes novads",
      "iso": "LV-077",
      "category": "municipality"
    },
    {
      "name": "Riebiņu novads",
      "iso": "LV-078",
      "category": "municipality"
    },
    {
      "name": "Rojas novads",
      "iso": "LV-079",
      "category": "municipality"
    },
    {
      "name": "Ropažu novads",
      "iso": "LV-080",
      "category": "municipality"
    },
    {
      "name": "Rucavas novads",
      "iso": "LV-081",
      "category": "municipality"
    },
    {
      "name": "Rugāju novads",
      "iso": "LV-082",
      "category": "municipality"
    },
    {
      "name": "Rundāles novads",
      "iso": "LV-083",
      "category": "municipality"
    },
    {
      "name": "Rūjienas novads",
      "iso": "LV-084",
      "category": "municipality"
    },
    {
      "name": "Salas novads",
      "iso": "LV-085",
      "category": "municipality"
    },
    {
      "name": "Salacgrīvas novads",
      "iso": "LV-086",
      "category": "municipality"
    },
    {
      "name": "Salaspils novads",
      "iso": "LV-087",
      "category": "municipality"
    },
    {
      "name": "Saldus novads",
      "iso": "LV-088",
      "category": "municipality"
    },
    {
      "name": "Saulkrastu novads",
      "iso": "LV-089",
      "category": "municipality"
    },
    {
      "name": "Sējas novads",
      "iso": "LV-090",
      "category": "municipality"
    },
    {
      "name": "Siguldas novads",
      "iso": "LV-091",
      "category": "municipality"
    },
    {
      "name": "Skrīveru novads",
      "iso": "LV-092",
      "category": "municipality"
    },
    {
      "name": "Skrundas novads",
      "iso": "LV-093",
      "category": "municipality"
    },
    {
      "name": "Smiltenes novads",
      "iso": "LV-094",
      "category": "municipality"
    },
    {
      "name": "Stopiņu novads",
      "iso": "LV-095",
      "category": "municipality"
    },
    {
      "name": "Strenču novads",
      "iso": "LV-096",
      "category": "municipality"
    },
    {
      "name": "Talsu novads",
      "iso": "LV-097",
      "category": "municipality"
    },
    {
      "name": "Tērvetes novads",
      "iso": "LV-098",
      "category": "municipality"
    },
    {
      "name": "Tukuma novads",
      "iso": "LV-099",
      "category": "municipality"
    },
    {
      "name": "Vaiņodes novads",
      "iso": "LV-100",
      "category": "municipality"
    },
    {
      "name": "Valkas novads",
      "iso": "LV-101",
      "category": "municipality"
    },
    {
      "name": "Varakļānu novads",
      "iso": "LV-102",
      "category": "municipality"
    },
    {
      "name": "Vārkavas novads",
      "iso": "LV-103",
      "category": "municipality"
    },
    {
      "name": "Vecpiebalgas novads",
      "iso": "LV-104",
      "category": "municipality"
    },
    {
      "name": "Vecumnieku novads",
      "iso": "LV-105",
      "category": "municipality"
    },
    {
      "name": "Ventspils novads",
      "iso": "LV-106",
      "category": "municipality"
    },
    {
      "name": "Viesītes novads",
      "iso": "LV-107",
      "category": "municipality"
    },
    {
      "name": "Viļakas novads",
      "iso": "LV-108",
      "category": "municipality"
    },
    {
      "name": "Viļānu novads",
      "iso": "LV-109",
      "category": "municipality"
    },
    {
      "name": "Zilupes novads",
      "iso": "LV-110",
      "category": "municipality"
    },
    {
      "name": "Daugavpils",
      "iso": "LV-DGV",
      "category": "republican city"
    },
    {
      "name": "Jelgava",
      "iso": "LV-JEL",
      "category": "republican city"
    },
    {
      "name": "Jēkabpils",
      "iso": "LV-JKB",
      "category": "republican city"
    },
    {
      "name": "Jūrmala",
      "iso": "LV-JUR",
      "category": "republican city"
    },
    {
      "name": "Liepāja",
      "iso": "LV-LPX",
      "category": "republican city"
    },
    {
      "name": "Rēzekne",
      "iso": "LV-REZ",
      "category": "republican city"
    },
    {
      "name": "Rīga",
      "iso": "LV-RIX",
      "category": "republican city"
    },
    {
      "name": "Valmiera",
      "iso": "LV-VMR",
      "category": "republican city"
    },
    {
      "name": "Ventspils",
      "iso": "LV-VEN",
      "category": "republican city"
    }
  ],
  "zipRegex": "^[L]{1}[V]{1}[-]([0-9]){4}$"
}